django_frontend-1.8.0.dist-info/DESCRIPTION.rst
django_frontend-1.8.0.dist-info/METADATA
django_frontend-1.8.0.dist-info/metadata.json
django_frontend-1.8.0.dist-info/RECORD
django_frontend-1.8.0.dist-info/top_level.txt
django_frontend-1.8.0.dist-info/WHEEL
djfrontend/__init__.py
djfrontend/__init__.pyc
djfrontend/apps.py
djfrontend/apps.pyc
djfrontend/models.py
djfrontend/models.pyc
djfrontend/static/djfrontend/css/fontawesome/4.3.0/font-awesome.css
djfrontend/static/djfrontend/css/fontawesome/4.3.0/font-awesome.min.css
djfrontend/static/djfrontend/css/fontawesome/4.6.3/font-awesome.css
djfrontend/static/djfrontend/css/fontawesome/4.6.3/font-awesome.css.map
djfrontend/static/djfrontend/css/fontawesome/4.6.3/font-awesome.min.css
djfrontend/static/djfrontend/css/h5bp/5.0.0/h5bp.css
djfrontend/static/djfrontend/css/h5bp/5.2.0/h5bp.css
djfrontend/static/djfrontend/css/h5bp/5.3.0/h5bp.css
djfrontend/static/djfrontend/css/jquery/jquery.dataTables/1.10.12/jquery.dataTables.css
djfrontend/static/djfrontend/css/jquery/jquery.dataTables/1.10.12/jquery.dataTables.min.css
djfrontend/static/djfrontend/css/jquery/jquery.dataTables/1.10.12/jquery.dataTables_themeroller.css
djfrontend/static/djfrontend/css/jquery/jquery.dataTables/1.10.5/jquery.dataTables.css
djfrontend/static/djfrontend/css/jquery/jquery.dataTables/1.10.5/jquery.dataTables.min.css
djfrontend/static/djfrontend/css/jquery/jquery.dataTables/1.10.5/jquery.dataTables_themeroller.css
djfrontend/static/djfrontend/css/jquery/jquery.dataTables/1.10.7/jquery.dataTables.css
djfrontend/static/djfrontend/css/jquery/jquery.dataTables/1.10.7/jquery.dataTables.min.css
djfrontend/static/djfrontend/css/jquery/jquery.dataTables/1.10.7/jquery.dataTables_themeroller.css
djfrontend/static/djfrontend/css/normalize/3.0.2/normalize.css
djfrontend/static/djfrontend/css/normalize/3.0.3/normalize.css
djfrontend/static/djfrontend/css/normalize/4.2.0/normalize.css
djfrontend/static/djfrontend/css/twbs/3.3.4/bootstrap-theme.css
djfrontend/static/djfrontend/css/twbs/3.3.4/bootstrap-theme.css.map
djfrontend/static/djfrontend/css/twbs/3.3.4/bootstrap-theme.min.css
djfrontend/static/djfrontend/css/twbs/3.3.4/bootstrap.css
